{
  "SallyPokehellHero-SallyPokehellHero DisplayName": "莎莉口袋妖怪英雄",
  "SallyPokehellHero-SallyPokehellHero DisplayDescription": "将来自 Pokehell 的莎莉添加到《气球塔防 6》中作为新英雄！",
  "SallyPokehellHero-Sally Level 2": "2级",
  "SallyPokehellHero-Sally Level 2s": "2级",
  "SallyPokehellHero-Sally Level 2 Description": "增加爆破力。",
  "SallyPokehellHero-Sally Level 3": "3级",
  "SallyPokehellHero-Sally Level 3s": "3级",
  "SallyPokehellHero-Sally Level 3 Description": "[Sizzly Shots]：投掷超热别针，造成 +1 伤害，具有 +1 穿透力，并且可以弹出任何类型的气球。该能力还允许附近的钉枪射击者击中除迷彩外的所有气球类型。",
  "Sizzly Shots": "热辣镜头",
  "Sizzly Shot": "铁板烧",
  "Sizzly Shots Description": "投掷超热别针，造成 +1 伤害，具有 +1 穿透力，并且可以弹出任何类型的气球。该能力还允许附近的钉枪射击者击中除迷彩外的所有气球类型。",
  "Sizzly Shots Alt Description": "投掷超热别针，造成 +100% 伤害，具有 +1 穿透力，并且可以弹出任何类型的气球。该能力还允许附近的钉枪射击者击中除迷彩外的所有气球类型。 13 级时为附近的钉枪射手提供双倍攻击速度",
  "Buzzy Blitz": "嗡嗡声闪电战",
  "Buzzy Blitzs": "热闹的闪电战",
  "Buzzy Blitz Description": "投掷激光尖针，使气球在被击中 1 秒后再次弹出，并且可以弹出任何类型的气球。该能力还允许附近的钉枪射击者击中除迷彩外的所有气球类型。",
  "Bouncy Bubble": "弹力泡泡",
  "Bouncy Bubbles": "弹力泡泡",
  "Bouncy Bubble Description": "投掷气泡别针，击中时会爆炸，造成 1 点伤害，移除迷彩和再生并弹出 [ft_leadbloonstitle]。该能力还允许附近的钉枪射击者击中除迷彩外的所有气球类型。",
  "SallyPokehellHero-Sally Level 4": "4级",
  "SallyPokehellHero-Sally Level 4s": "4级",
  "SallyPokehellHero-Sally Level 4 Description": "增加攻击范围。",
  "SallyPokehellHero-Sally Level 5": "5级",
  "SallyPokehellHero-Sally Level 5s": "5级",
  "SallyPokehellHero-Sally Level 5 Description": "[SallyPokehellHero-Sally] 可以检测迷彩气球。还允许半径内的所有 [TackShooters] 和 Eevee 攻击 [ft_camobloonstitle]。",
  "SallyPokehellHero-Sally Level 6": "6级",
  "SallyPokehellHero-Sally Level 6s": "6级",
  "SallyPokehellHero-Sally Level 6 Description": "莎莉的别针可能会弹出[ft_frozenbloonstitle]。",
  "SallyPokehellHero-Sally Level 7": "7级",
  "SallyPokehellHero-Sally Level 7s": "7级",
  "ft_frozenbloonstitle": "冰冻气球",
  "SallyPokehellHero-Sally Level 7 Description": "增加爆破力。范围内的所有塔都获得 +1 穿透力。",
  "SallyPokehellHero-Sally Level 8": "8级",
  "SallyPokehellHero-Sally Level 8s": "8级",
  "SallyPokehellHero-Sally Level 8 Description": "一次抛出 5 个针。",
  "SallyPokehellHero-Sally Level 9": "9级",
  "SallyPokehellHero-Sally Level 9s": "9级",
  "SallyPokehellHero-Sally Level 9 Description": "攻击速度增加。",
  "SallyPokehellHero-Sally Level 10": "10级",
  "SallyPokehellHero-Sally Level 10s": "10级",
  "SallyPokehellHero-Sally Level 10 Description": "[Freezy Frost]：发射冰柱，能够冻结[ft_moabclassbloonstitle]",
  "Freezy Frost": "冰霜",
  "Freezy Frosts": "冰霜",
  "FreezyFrost Description": "发射一些爆炸性种子，造成 325% 的伤害，能够击晕许多气球",
  "FreezyFrost Alt Description": "发射冰柱造成 1000% 伤害，能够冻结 [ft_moabclassbloonstitle]",
  "Sappy Seed": "多汁的种子",
  "Sappy Seeds": "多汁的种子",
  "Minty Icicle": "薄荷冰柱",
  "Minty Icicles": "薄荷冰柱",
  "Minty Icicle Description": "发射高穿透力冰柱，造成 200% 伤害，能够弹射到许多目标",
  "SallyPokehellHero-Sally Level 11": "11级",
  "SallyPokehellHero-Sally Level 11s": "11级",
  "SallyPokehellHero-Sally Level 11 Description": "增加攻击范围。",
  "SallyPokehellHero-Sally Level 12": "12级",
  "SallyPokehellHero-Sally Level 12s": "12级",
  "SallyPokehellHero-Sally Level 12 Description": "[气球流血]：每10次攻击会造成持续缓慢伤害的效果。",
  "SallyPokehellHero-Sally Level 13": "13级",
  "SallyPokehellHero-Sally Level 13s": "13级",
  "Bloon Bleed": "气球流血",
  "Bloon Bleeds": "气球流血",
  "Bloon Bleed Description": "每 2.0 秒造成 1 点伤害，或每 2.0 秒造成 20 MOAB 级伤害，持续最多 4 秒。",
  "SallyPokehellHero-Sally Level 13 Description": "永久抛出超热销。 [冰冻]影响铅气球。 [猛烈射击]现在提供双倍攻击速度。",
  "SallyPokehellHero-Sally Level 14": "14级",
  "SallyPokehellHero-Sally Level 14s": "14级",
  "SallyPokehellHero-Sally Level 14 Description": "别针对 [ft_moabclassbloonstitle] 造成 +4 伤害。",
  "SallyPokehellHero-Sally Level 15": "15级",
  "SallyPokehellHero-Sally Level 15s": "15级",
  "SallyPokehellHero-Sally Level 15 Description": "技能冷却时间减少 15%。",
  "SallyPokehellHero-Sally Level 16": "16级",
  "SallyPokehellHero-Sally Level 16s": "16级",
  "SallyPokehellHero-Sally Level 16 Description": "[气球流血]2：每5次攻击会造成持续缓慢伤害的效果。",
  "SallyPokehellHero-Sally Level 17": "17级",
  "SallyPokehellHero-Sally Level 17s": "17级",
  "SallyPokehellHero-Sally Level 17 Description": "增加爆破力。范围内的所有塔受到 +1 伤害",
  "SallyPokehellHero-Sally Level 18": "18级",
  "SallyPokehellHero-Sally Level 18s": "18级",
  "SallyPokehellHero-Sally Level 18 Description": "每次击中别针会弹出两倍的气球层。",
  "SallyPokehellHero-Sally Level 19": "19级",
  "SallyPokehellHero-Sally Level 19s": "19级",
  "SallyPokehellHero-Sally Level 19 Description": "一次扔8个针。",
  "SallyPokehellHero-Sally Level 20": "20级",
  "SallyPokehellHero-Sally Level 20s": "20级",
  "SallyPokehellHero-Sally Level 20 Description": "[气球流血]加：每第四次攻击会造成一段时间内的缓慢伤害效果，并弹出两倍层的气球。技能冷却时间减少 15%。别针对 [ft_moabclassbloonstitle] 造成的伤害增加 +5。",
  "SallyPokehellHero-Sally": "莎莉",
  "SallyPokehellHero-Sallys": "莎莉丝",
  "SallyPokehellHero-Sally Description": "莎莉向气球扔别针，同时支持其他猴子，特别是[TackShooters]。",
  "SallyPokehellHero-Sally Short Description": "伊布",
  "SallyPokehellHero-Sally Level 1 Description": "快速向气球扔别针。半径内的所有 [TackShooters] 都会获得更大的射程。"
}
